llmratelimiter/__init__.py
llmratelimiter/config.py
llmratelimiter/connection.py
llmratelimiter/limiter.py
llmratelimiter/models.py
llmratelimiter/scripts.py
llmratelimiter-0.3.2.dist-info/METADATA
llmratelimiter-0.3.2.dist-info/WHEEL
llmratelimiter-0.3.2.dist-info/licenses/LICENSE
llmratelimiter-0.3.2.dist-info/RECORD
