Metadata-Version: 2.4
Name: LLMRateLimiter
Version: 0.3.2
Summary: Rate limiter for LLM
Project-URL: Homepage, https://Ameyanagi.github.io/LLMRateLimiter/
Project-URL: Repository, https://github.com/Ameyanagi/LLMRateLimiter
Project-URL: Documentation, https://Ameyanagi.github.io/LLMRateLimiter/
Author-email: Ameyanagi <contact@ameyanagi.com>
License-File: LICENSE
Keywords: python
Classifier: Intended Audience :: Developers
Classifier: Programming Language :: Python
Classifier: Programming Language :: Python :: 3
Classifier: Programming Language :: Python :: 3.12
Classifier: Programming Language :: Python :: 3.13
Classifier: Topic :: Software Development :: Libraries :: Python Modules
Requires-Python: <4.0,>=3.12
Requires-Dist: redis>=5.0.0
